{
  "config": {
    "abort": {
      "already_configured": "L'appareil est déjà configuré",
      "already_in_progress": "La configuration est déjà en cours",
      "no_devices_found": "Aucun appareil trouvé sur le réseau"
    },
    "flow_title": "{name}",
    "step": {
      "bluetooth_confirm": {
        "description": "Voulez-vous configurer {name} ?"
      },
      "user": {
        "data": {
          "address": "Appareil"
        },
        "description": "Sélectionnez l'appareil à configurer"
      }
    }
  }
}
